stix_shifter_modules/secretserver/__init__.py
stix_shifter_modules/secretserver/entry_point.py
stix_shifter_modules/secretserver/configuration/config.json
stix_shifter_modules/secretserver/configuration/dialects.json
stix_shifter_modules/secretserver/configuration/lang_en.json
stix_shifter_modules/secretserver/stix_translation/__init__.py
stix_shifter_modules/secretserver/stix_translation/json_to_stix_translator.py
stix_shifter_modules/secretserver/stix_translation/query_constructor.py
stix_shifter_modules/secretserver/stix_translation/query_translator.py
stix_shifter_modules/secretserver/stix_translation/json/event_from_stix_map.json
stix_shifter_modules/secretserver/stix_translation/json/operators.json
stix_shifter_modules/secretserver/stix_translation/json/to_stix_map.json
stix_shifter_modules/secretserver/stix_translation/json/stix_2_1/event_from_stix_map.json
stix_shifter_modules/secretserver/stix_translation/json/stix_2_1/to_stix_map.json
stix_shifter_modules/secretserver/stix_transmission/__init__.py
stix_shifter_modules/secretserver/stix_transmission/api_client.py
stix_shifter_modules/secretserver/stix_transmission/delete_connector.py
stix_shifter_modules/secretserver/stix_transmission/error_mapper.py
stix_shifter_modules/secretserver/stix_transmission/ping_connector.py
stix_shifter_modules/secretserver/stix_transmission/query_connector.py
stix_shifter_modules/secretserver/stix_transmission/results_connector.py
stix_shifter_modules_secretserver-8.0.2.dist-info/licenses/AUTHORS.md
stix_shifter_modules_secretserver-8.0.2.dist-info/licenses/LICENSE.md
stix_shifter_modules_secretserver-8.0.2.dist-info/licenses/NOTICE
stix_shifter_modules_secretserver-8.0.2.dist-info/METADATA
stix_shifter_modules_secretserver-8.0.2.dist-info/WHEEL
stix_shifter_modules_secretserver-8.0.2.dist-info/top_level.txt
stix_shifter_modules_secretserver-8.0.2.dist-info/RECORD
